README.md
setup.py
nospy/__init__.py
nospy.egg-info/PKG-INFO
nospy.egg-info/SOURCES.txt
nospy.egg-info/dependency_links.txt
nospy.egg-info/requires.txt
nospy.egg-info/top_level.txt