Metadata-Version: 2.1
Name: nospy
Version: 0.0.1.post1
Summary: Network Object Store
Home-page: https://github.com/dsikes/nospy
Author: Dan Sikes
Author-email: dsikes@atlantean.io
License: UNKNOWN
Project-URL: Source, https://github.com/dsikes/nospy
Keywords: network object store binary data datastore fast
Platform: UNKNOWN
